{
  "0": "Agbalumo-Regular",
  "1": "AlfaSlabOne-Regular",
  "10": "Courier",
  "11": "Georgia",
  "12": "Helvetica",
  "13": "IBMPlexSans-Regular",
  "14": "Inter-Regular",
  "15": "KaushanScript-Regular",
  "16": "Lato-Regular",
  "17": "Lobster-Regular",
  "18": "Lora-Regular",
  "19": "Merriweather-Regular",
  "2": "ArchitectsDaughter-Regular",
  "20": "Niconne-Regular",
  "21": "OpenSans-Bold",
  "22": "OpenSans-Italic",
  "23": "OpenSans-Light",
  "24": "Pacifico-Regular",
  "25": "PixelifySans-Regular",
  "26": "PlayfairDisplay-Regular",
  "27": "Poppins-Regular",
  "28": "Rakkas-Regular",
  "29": "Roboto-Regular",
  "3": "Arial",
  "30": "RobotoMono-Regular",
  "31": "RobotoSlab-Regular",
  "32": "Rubik-Regular",
  "33": "SpaceMono-Regular",
  "34": "Tahoma",
  "35": "Tahoma Bold",
  "36": "Times New Roman",
  "37": "Times New Roman Bold",
  "38": "Times New Roman Bold Italic",
  "39": "Times New Roman Italic",
  "4": "Arial Black",
  "40": "TitilliumWeb-Regular",
  "41": "Trebuchet MS",
  "42": "Trebuchet MS Bold",
  "43": "Trebuchet MS Bold Italic",
  "44": "Trebuchet MS Italic",
  "45": "Verdana",
  "46": "Verdana Bold",
  "47": "Verdana Bold Italic",
  "48": "Verdana Italic",
  "5": "Arial Bold",
  "6": "Arial Bold Italic",
  "7": "Avenir",
  "8": "Bangers-Regular",
  "9": "BlackOpsOne-Regular"
}